{
  "version": "1.0.25",
  "lastUpdated": {
    "date": "2026-03-27",
    "time": "21:04"
  },
  "entries": [
    {
      "version": "1.0.25",
      "date": "2026-03-27",
      "changes": [
        "update in-app roadmap after Phase 1-5 delivery"
      ]
    },
    {
      "version": "1.0.24",
      "date": "2026-03-27",
      "changes": []
    },
    {
      "version": "1.0.23",
      "date": "2026-03-27",
      "changes": [
        "Phase 5 — meal planner + offline QR code sharing",
        "Phase 4 — ingredient search + PDF export",
        "Phase 3c — ingredient dictionary + shopping list"
      ]
    },
    {
      "version": "1.0.22",
      "date": "2026-03-27",
      "changes": [
        "Phase 3c — ingredient dictionary + shopping list with multi-recipe aggregation",
        "Phase 4 — PDF export with QR code, ingredient-based recipe search",
        "Phase 5 — meal planner (7-day view), offline QR code sharing with recipe JSON",
        "fix route ordering for shopping list delete endpoints",
        "fix SPA fallback — direct navigation to /shopping, /planner, /scan now works",
        "fix shopping list item display (Drizzle ORM camelCase → snake_case serialization)",
        "fix shopping list race condition on pending items",
        "fix checked shopping items now visible with strikethrough",
        "fix QR decode array validation",
        "fix PDF export page overflow in notes section"
      ]
    },
    {
      "version": "1.0.21",
      "date": "2026-03-27",
      "changes": [
        "copy .npmrc into all Dockerfile stages before npm ci"
      ]
    },
    {
      "version": "1.0.20",
      "date": "2026-03-26",
      "changes": [
        "add .npmrc with legacy-peer-deps for vite-plugin-pwa peer dep conflict"
      ]
    },
    {
      "version": "1.0.19",
      "date": "2026-03-26",
      "changes": [
        "Phase 3b — photo import (camera/gallery → AI extraction)",
        "show star rating in recipe detail header and list/grid views",
        "Phase 3a — recipe rating (1–5 stars) + personal notes",
        "cook mode responsive layout — sidebar on desktop, improved drawer on mobile",
        "Phase 2 — PWA setup + Fullscreen Cook Mode",
        "Phase 1 — polished core fixes"
      ]
    },
    {
      "version": "1.0.18",
      "date": "2026-03-25",
      "changes": [
        "remove performance-test references and add missing newline"
      ]
    },
    {
      "version": "1.0.16",
      "date": "2026-03-25",
      "changes": [
        "increase serving size stepper buttons from w-4 to w-7"
      ]
    },
    {
      "version": "1.0.15",
      "date": "2026-03-25",
      "changes": [
        "correct created_at storage, date display and footer timezone"
      ]
    },
    {
      "version": "1.0.14",
      "date": "2026-03-25",
      "changes": [
        "correct recipe date display and changelog version numbers"
      ]
    },
    {
      "version": "1.0.13",
      "date": "2026-03-25",
      "changes": [
        "Zuverlässiger Docker-Deploy nach jedem Release"
      ]
    },
    {
      "version": "1.0.11",
      "date": "2026-03-25",
      "changes": [
        "Fehlerdetails bei Extraktion – Details-Button mit Kopier-Funktion",
        "Datumsanzeige bei Rezepten korrigiert"
      ]
    },
    {
      "version": "1.0.2",
      "date": "2026-03-25",
      "changes": [
        "Changelog & \"Zuletzt aktualisiert\" in der Fußzeile"
      ]
    },
    {
      "version": "1.0.1",
      "date": "2026-03-25",
      "changes": [
        "Mobile UI verbessert",
        "Auto-Changelog bei jedem Release"
      ]
    },
    {
      "version": "1.0.0",
      "date": "2026-03-25",
      "changes": [
        "Erstes Release – React-Frontend, Rezeptextraktion, BYOK, Docker-Deployment"
      ]
    }
  ]
}
